robologs_ros_utils/__init__.py
robologs_ros_utils/cli.py
robologs_ros_utils/sources/__init__.py
robologs_ros_utils/sources/ros1/__init__.py
robologs_ros_utils/sources/ros1/argument_parsers.py
robologs_ros_utils/sources/ros1/commands.py
robologs_ros_utils/sources/ros1/get_csv_data_from_bag.py
robologs_ros_utils/sources/ros1/get_images_from_bag.py
robologs_ros_utils/sources/ros1/get_summary_from_bag.py
robologs_ros_utils/sources/ros1/get_videos_from_bag.py
robologs_ros_utils/sources/ros1/ros_img_tools.py
robologs_ros_utils/sources/ros1/ros_utils.py
robologs_ros_utils/utils/__init__.py
robologs_ros_utils/utils/file_utils.py
robologs_ros_utils/utils/img_utils.py
robologs_ros_utils-0.1.1a61.dist-info/METADATA
robologs_ros_utils-0.1.1a61.dist-info/WHEEL
robologs_ros_utils-0.1.1a61.dist-info/entry_points.txt
robologs_ros_utils-0.1.1a61.dist-info/RECORD
