Metadata-Version: 2.1
Name: robologs-ros-utils
Version: 0.1.1a61
Summary: robologs-ros-utils is an open source library of containerized data transformations for the robotics and drone communities
License: Apache-2.0
Author: roboto.ai
Author-email: info@roboto.ai
Requires-Python: >=3.8.2,<4.0.0
Classifier: License :: OSI Approved :: Apache Software License
Classifier: Programming Language :: Python :: 3
Classifier: Programming Language :: Python :: 3.9
Classifier: Programming Language :: Python :: 3.10
Classifier: Programming Language :: Python :: 3.11
Requires-Dist: Flask (>=2,<3)
Requires-Dist: bagpy (>=0.5,<0.6)
Requires-Dist: black[d] (>=22.12.0,<23.0.0)
Requires-Dist: click (>=8.1.3,<9.0.0)
Requires-Dist: coverage (>=6.5.0,<7.0.0)
Requires-Dist: isort (>=5.11.2,<6.0.0)
Requires-Dist: nose (>=1.3.7,<2.0.0)
Requires-Dist: numpy (>=1.23.1,<2.0.0)
Requires-Dist: opencv-python (>=4.5.0.0,<5.0.0.0)
Requires-Dist: pydantic (>=1.10.2,<2.0.0)
Requires-Dist: pytest (>=7.2.0,<8.0.0)
Requires-Dist: pytest-datafiles (>=2.0.1,<3.0.0)
Requires-Dist: rosbags (>=0.9.13,<0.10.0)
Requires-Dist: tqdm (>=4.64.1,<5.0.0)
Requires-Dist: types-tqdm (>=4.64.7.9,<5.0.0.0)
